syne_ga_mcp/__init__.py
syne_ga_mcp/config.py
syne_ga_mcp/ga_handler.py
syne_ga_mcp/server.py
syne_ga_mcp-0.0.1.dist-info/METADATA
syne_ga_mcp-0.0.1.dist-info/WHEEL
syne_ga_mcp-0.0.1.dist-info/entry_points.txt
syne_ga_mcp-0.0.1.dist-info/RECORD
