Metadata-Version: 2.4
Name: syne_ga_mcp
Version: 0.0.1
Summary: MCP Server for Google Analytics Data API
Author-email: synehq <team@synehq.com>
Requires-Python: >=3.10
Requires-Dist: asyncio
Requires-Dist: google-analytics-admin<0.6.0,>=0.5.0
Requires-Dist: google-analytics-data<0.19.0,>=0.18.18
Requires-Dist: google-auth<3.0.0,>=2.38.0
Requires-Dist: mcp-server<0.2.0,>=0.1.4
Requires-Dist: pydantic<3.0.0,>=2.11.3
Requires-Dist: pydantic[email]
Requires-Dist: setuptools
Requires-Dist: typer[all]<0.16.0,>=0.15.2
Requires-Dist: uvicorn<0.24.0,>=0.23.0
